serverz/__init__.py
serverz/log.py
serverz/utils.py
serverz/core/chatbox.py
serverz/core/debug_agent.py
serverz/core/tools/__init__.py
serverz/core/tools/fc.py
serverz/core/tools/tools.py
serverz/server/__init__.py
serverz/server/__main__.py
serverz/server/models.py
serverz/server/scheduler_task.py
serverz/server/routers/__init__.py
serverz/server/routers/agent_debug.py
serverz/server/routers/chat.py
serverz-0.1.21.dist-info/METADATA
serverz-0.1.21.dist-info/WHEEL
serverz-0.1.21.dist-info/top_level.txt
serverz-0.1.21.dist-info/RECORD
