Metadata-Version: 2.4
Name: serverz
Version: 0.1.21
Summary: Add your description here
Requires-Python: >=3.12
Requires-Dist: agno>=2.3.2
Requires-Dist: anyio>=4.11.0
Requires-Dist: apscheduler>=3.11.0
Requires-Dist: deepagents>=0.1.4
Requires-Dist: fastapi>=0.118.0
Requires-Dist: mcp[cli]>=1.16.0
Requires-Dist: pymysql>=1.1.2
Requires-Dist: uvicorn>=0.37.0
